little_api/__init__.py
little_api/api.py
little_api/config.py
little_api/debug_server.py
little_api/exceptions.py
little_api/middleware.py
little_api/response.py
little_api/utils.py
tests/__init__.py
tests/conftest.py
tests/test_exception_handler.py
tests/test_middleware.py
tests/test_responses.py
tests/test_routes.py
tests/test_static_files.py
tests/test_templates.py
little_api-0.0.2.dist-info/METADATA
little_api-0.0.2.dist-info/WHEEL
little_api-0.0.2.dist-info/top_level.txt
little_api-0.0.2.dist-info/RECORD
