Metadata-Version: 2.1
Name: little-api
Version: 0.0.2
Summary: Little API the web framework that could
Home-page: UNKNOWN
Author: j dunham
Author-email: 
License: MIT
Platform: UNKNOWN
Classifier: Programming Language :: Python :: 3.6
Requires-Python: >=3.6.0
Requires-Dist: Jinja2 (==2.10.3)
Requires-Dist: parse (==1.12.1)
Requires-Dist: requests (==2.22.0)
Requires-Dist: requests-wsgi-adapter (==0.4.1)
Requires-Dist: WebOb (==1.8.5)
Requires-Dist: whitenoise (==4.1.4)
Requires-Dist: pyjwt (==2.0.1)
Requires-Dist: gunicorn (==20.0.4)
